{
  "updated": "2026-05-05",
  "source": "88st-cloud-consult-motive-v7-full-20260505.zip",
  "summary": "체스 신규 업체 추가 v8: 보증업체 카드, compact 모달, 상담 허브, 블로그 게시글, 검색 랜딩, 변경 이력, 상담 결과형 페이지 반영",
  "new_public_pages": [
    "/consult/chess/",
    "/blog/online-casino/chess-bti-sports-casino-slot-guide.html",
    "/search-guides/chess-seoa-code.html",
    "/provider-updates/chess-seoa.html",
    "/consult-result/chess-seoa-guide.html"
  ],
  "created_or_modified": [
    "PATCH_NOTES_20260505_CHESS_PROVIDER_V8.md",
    "assets/config/seo.meta.json",
    "assets/css/guaranteed.cards.v1.20260504.css",
    "assets/data/auto.consult.v1.20260505.json",
    "assets/data/conversion.boost.v4.20260505.json",
    "assets/data/guaranteed.providers.v1.20260330.json",
    "assets/data/provider.event-history.v1.20260505.json",
    "assets/data/search.keywords.v5.20260505.json",
    "assets/js/build.ver.js",
    "assets/js/conversion.boost.v4.20260505.js",
    "assets/js/hub.promo.compact.v6.20260505.js",
    "assets/provider-media/chess-event-01.jpeg",
    "assets/provider-media/chess-logo.png",
    "blog/index.html",
    "blog/online-casino/chess-bti-sports-casino-slot-guide.html",
    "build.txt",
    "consult-result/chess-seoa-guide.html",
    "consult-result/index.html",
    "consult/chess/index.html",
    "consult/index.html",
    "guaranteed/index.html",
    "index.html",
    "provider-updates/chess-seoa.html",
    "provider-updates/index.html",
    "search-guides/chess-seoa-code.html",
    "search-guides/index.html",
    "serverless/sitemap.txt",
    "serverless/sitemap.xml",
    "sitemap.txt",
    "sitemap.xml",
    "tools/today-check/index.html"
  ],
  "deleted_from_full": []
}